mtcnn/__init__.py
mtcnn/metadata.py
mtcnn/mtcnn.py
mtcnn/assets/weights/onet.lz4
mtcnn/assets/weights/pnet.lz4
mtcnn/assets/weights/rnet.lz4
mtcnn/network/__init__.py
mtcnn/network/onet.py
mtcnn/network/pnet.py
mtcnn/network/rnet.py
mtcnn/stages/__init__.py
mtcnn/stages/base.py
mtcnn/stages/stage_onet.py
mtcnn/stages/stage_pnet.py
mtcnn/stages/stage_rnet.py
mtcnn/utils/__init__.py
mtcnn/utils/bboxes.py
mtcnn/utils/images.py
mtcnn/utils/landmarks.py
mtcnn/utils/plotting.py
mtcnn/utils/tensorflow.py
mtcnn-1.0.0.dist-info/LICENSE
mtcnn-1.0.0.dist-info/METADATA
mtcnn-1.0.0.dist-info/WHEEL
mtcnn-1.0.0.dist-info/top_level.txt
mtcnn-1.0.0.dist-info/RECORD
