Metadata-Version: 2.1
Name: mtcnn
Version: 1.0.0
Summary: Multitask Cascaded Convolutional Networks for face detection and alignment (MTCNN) in Python >= 3.10 and TensorFlow >= 2.12
Home-page: https://github.com/ipazc/mtcnn
Author: Iván de Paz Centeno
Author-email: ipazc@unileon.es
License: MIT
Project-URL: Documentation, https://github.com/ipazc/mtcnn/docs
Project-URL: Source, https://github.com/ipazc/mtcnn
Project-URL: Tracker, https://github.com/ipazc/mtcnn/issues
Classifier: Development Status :: 4 - Beta
Classifier: Intended Audience :: Developers
Classifier: Intended Audience :: Science/Research
Classifier: License :: OSI Approved :: MIT License
Classifier: Programming Language :: Python :: 3.10
Classifier: Programming Language :: Python :: 3.11
Classifier: Programming Language :: Python :: 3.12
Classifier: Topic :: Scientific/Engineering :: Artificial Intelligence
Requires-Python: >=3.10
License-File: LICENSE
Requires-Dist: joblib>=1.4.2
Requires-Dist: lz4>=4.3.3
Provides-Extra: tensorflow
Requires-Dist: tensorflow>=2.12.0; extra == "tensorflow"
Provides-Extra: dev
Requires-Dist: pytest>=8.3.3; extra == "dev"
Requires-Dist: pytest-cov>=5.0.0; extra == "dev"
Requires-Dist: mkdocs>=1.6.1; extra == "dev"
Requires-Dist: mkdocs-material>=9.5.39; extra == "dev"
Requires-Dist: mkdocs-jupyter>=0.25.0; extra == "dev"
